steamwrapper/__init__.py
steamwrapper/steamwrapper.py
steamwrapper-0.1262.dist-info/METADATA
steamwrapper-0.1262.dist-info/RECORD
steamwrapper-0.1262.dist-info/WHEEL
steamwrapper-0.1262.dist-info/top_level.txt
