Metadata-Version: 2.1
Name: steamwrapper
Version: 0.1262
Summary: API wrapper for Steam written in Python
Home-page: https://github.com/truedl/steamwrapper
Author: truedl
Author-email: dauzduz1@gmail.com
License: MIT
Platform: UNKNOWN
Requires-Dist: requests
Requires-Dist: aiohttp
